{
  "general_info": {
    "uuid": "b3a2f1e0-d9c8-4b7a-6f5e-4d3c2b1a0f9e",
    "brand": "FR 8 WP",
    "manufacturer": "Visaton",
    "providedby": "SiVAL",
    "comment": "Daten aus roher Spezifikationsliste, umgerechnet in SI-Einheiten und an Schema angepasst.",
    "model": "FR 8 WP - 4 Ohm",
    "indexed": false
  },
  "electrical_parameters": {
    "impedance": { "value": 4.0, "unit": "Ohm" },
    "sensitivity": { "value": 83.9, "unit": "dB" },
    "re": { "value": 4.1, "unit": "Ohm" },
    "le": { "value": 0.0003, "unit": "H" },
    "znom": { "value": 4.0, "unit": "Ohm" },
    "pe": { "value": 15.0, "unit": "W" },
    "pmax": { "value": 25.0, "unit": "W" },
    "bl": { "value": 2.8, "unit": "Tm" },
    "motor_constant": { "value": 1.38, "unit": "N/sqrt(W)" },
    "flux_density": { "value": 1.0, "unit": "T" }
  },
  "thiele_small_parameters": {
    "fs": { "value": 158.0, "unit": "Hz" },
    "qms": 2.62,
    "qes": 1.33,
    "qts": 0.88,
    "mms": { "value": 0.0029, "unit": "kg" },
    "mmd": { "value": 0.0028, "unit": "kg" },
    "stiffness": { "value": 3200.0, "unit": "N/m" },
    "cms": { "value": 0.000313, "unit": "m/N" },
    "vas": { "value": 0.0004, "unit": "m3" },
    "rms": { "value": 1.1, "unit": "kg/s" },
    "sd": { "value": 0.003, "unit": "m2" },
    "xmax": { "value": 0.5, "unit": "mm" },
    "xlim": { "value": 3.0, "unit": "mm" },
    "vd": { "value": 0.0000015, "unit": "m3" }
  },
  "physical_dimensions": {
    "vc_diameter": { "value": 20.0, "unit": "mm" },
    "winding_height": { "value": 4.0, "unit": "mm" },
    "air_gap_height": { "value": 3.0, "unit": "mm" },
    "effective_diameter": { "value": 62.0, "unit": "mm" },
    "nominal_diameter": "3.3″",
    "baffle_cutout_diameter": { "value": 74.0, "unit": "mm" },
    "volume_occupied": null,
    "net_weight": { "value": 0.23, "unit": "kg" },
    "material": "Waterproof"
  }
}